pushman/__init__.py
pushman/compat.py
pushman/main.py
pushman-1.0.2.dist-info/METADATA
pushman-1.0.2.dist-info/RECORD
pushman-1.0.2.dist-info/WHEEL
pushman-1.0.2.dist-info/top_level.txt
